MANIFEST.in
README.txt
setup.cfg
setup.py
deploy_commander/__init__.py
deploy_commander/api.py
deploy_commander/config.py
deploy_commander/main.py
deploy_commander/test.py
deploy_commander/utils.py
deploy_commander.egg-info/PKG-INFO
deploy_commander.egg-info/SOURCES.txt
deploy_commander.egg-info/dependency_links.txt
deploy_commander.egg-info/entry_points.txt
deploy_commander.egg-info/not-zip-safe
deploy_commander.egg-info/requires.txt
deploy_commander.egg-info/top_level.txt
deploy_commander/command/__init__.py
deploy_commander/command/aptget.py
deploy_commander/command/git.py
deploy_commander/command/mysql.py
deploy_commander/command/system.py
deploy_commander/fabfile/__init__.py