Metadata-Version: 1.1
Name: deploy-commander
Version: 0.1.20
Summary: Simple command line tool to deploy your projects
Home-page: http://deploy-commander.readthedocs.org
Author: Ference van Munster
Author-email: info@munstermedia.nl
License: Free
Platform: UNKNOWN
Classifier: Development Status :: 3 - Alpha
Classifier: Intended Audience :: Developers
Classifier: Topic :: Software Development :: Build Tools
Classifier: Programming Language :: Python :: 2.7
Classifier: Programming Language :: Python :: 3
